[{"content":"","date":null,"permalink":"/tags/","section":"标签","summary":"","title":"#数学分析"},{"content":"标签如下 #","date":null,"permalink":"/tags/","section":"标签","summary":"标签如下 #","title":"标签"},{"content":"简要的描述一下第二章的主要内容，涉及到傅立叶级数研究的对象，提出傅立叶级数的收敛性与唯一性问题，并由收敛性问题引申出级数求和的新方式。\n主要矛盾：傅立叶分析研究的对象 #傅立叶分析研究的主要对象是定义在区间或者圆上的至少为黎曼可积的函数。这类函数的特点是有界，但可以有无穷多个间断点。\n对于定义在长度为 \\(2\\pi\\) 上的周期函数 $f(\\theta)$ ，我们可以将它定义到圆上，得到对应的 $F(e^{i\\theta})$ ， $\\theta$ 是 $2\\pi$ 整数倍区间上的一个实数。因为 $F(e^{i\\theta})$ 是 $f(\\theta)$ 的一个变型，所以它的连续性、可积性以及其他光滑特性都没有改变。当函数定义在区间上时，一般用 $x$ 表示自变量，当定义在圆上时，则用 $\\theta$ 来代替 $x$ 。\n定义在长度为 $L$ 的区间 $[a,b]$ 上的连续函数 $f(x)$ 的傅立叶系数 $a$ 定义为 $$\ra_{n}=\\hat{f}(n)= \\frac{1}{L}\\int _{0}^Lf(x)e^{-i2\\pi nx /L} \\, \\text{d}x ,$$ 它的含义是第 $n$ 个系数等于 $f(x)$ 与频率为 ${2\\pi n}$ 的复指数函数 $\\varphi_{n}(x)= e^{i2\\pi nx /L}$ 的內积： $\\frac{1}{L}\\left\u003c f(x),e^{i2\\pi nx /L} \\right\u003e$ 。\n镜中故我？：唯一性和收敛性的问题、Kernel #以上只是通过 $f(x)$ 找到了它的傅立叶级数，但是仍需要回答两个问题，第一这个傅立叶级数，它保收敛吗？如果我们拿着 $f(x)$ 一顿计算，结果最后级数发散了，那不白忙活了吗？这个问题看起来比较复杂，实际一点也不简单，因为系数中的 $f(x)$ 是纯粹形式（pure formal）上的，我们无法看出到底是不是收敛的。当然，系数表达式中的复指数函数以及求和不是 pure formal 的，我们可以在它们上面做一些文章。\n先短暂跳过收敛性的讨论，我们面临的第二个问题是如果得到了在某个意义上收敛的傅立叶级数，那么这个傅立叶级数是唯一的吗？或者说：具有相同傅立叶系数的两个函数必然相等吗？这来自于人们的朴素愿望，我们通过变换得到函数在另一个空间的表达，但它在重新换到原空间时应该是不变的，或者至少只有很小一部分（零测度集）和原先不同。\n答案是，在这两个函数的连续点处，它们是相等的。\n接下来回到收敛性问题：函数的傅立叶级数是否收敛于原函数？这个问题的另一个表述是傅立叶级数的部分和 $S_{n}$ 在 $n\\to \\infty$ 时是否收敛于 $f(x)$ 。为此，我们将深入研究傅立叶级数的部分和。\n假设 $f(x)$ 是定义在 $[-\\pi,\\pi]$ 上的函数。首先，观察它傅立叶级数部分和的公式，它是由 $a\\_{n}$ 和不同频率的复指数函数相乘再求和得到： $S_{N}(x)=\\sum_{n=-N}^Na_{n}e^{i nx}$ ，而 $a_{n}$ 的积分内又包含了一个 $\\varphi_{n}^*(y)=e^{-i ny}$ ，如果将 $\\varphi_{n}^*(y)\\varphi_{n}(x)$ 结合，将函数 $f(x)$ 视作一个变量，那么部分和可以等价于 $f(x)$ 和一个系统函数（或者说，Kernel）的卷积，部分和的变换方法是这样的： $$\\begin{aligned}S_{N}(x)\u0026=\\sum_{n=-N}^Na_{n}e^{inx}\\\\\u0026=\\sum_{n=-N}^N\\left( \\frac{1}{2\\pi}\\int _{a}^bf(y)e^{-iny} \\, \\text{d}y \\right) \\cdot e^{inx}\\\\\u0026=\\frac{1}{2\\pi}\\sum_{n=-N}^N\\int _{a}^b f(y)e^{in(x-y)} \\, \\text{d}y\\\\\u0026=\\frac{1}{2\\pi}\\int _{a}^b\\left( \\sum_{n=-N}^Ne^{in(x-y)} \\right)f(y) \\, \\text{d}y , \\end{aligned}$$ 第三个等号是因为积分与 $x$ 无关，所以 $e^{inx}$ 可以放到积分内部，第四个等号是因为 $\\sum_{n=-N}^Ne^{iny}$ 是一致收敛的，所以求和号可以换到积分里去（ $f(y)$ 与 $n$ 无关，所以不需要考虑 $f(y)$ ）。\n将两个周期是 $2\\pi$ ，定义域是 $[-\\pi,\\pi]$ 的函数的卷积定义为： $f(x)* g(x)=\\frac{1}{2\\pi}\\int _{-\\pi}^\\pi f(y)g(x-y) \\, \\text{d}y$ ，那么部分和可以写为 $S_{N}(x)=D_{N}(x)*f(x)$ ，其中 $D_{N}=\\sum_{n=-N}^Ne^{inx}$ 被当做生成部分和的 Kernel，称为 Dirichlet Kernel。多说一句，这里的卷积定义多了一个 $\\frac{1}{2\\pi}$ 的系数，这样部分和可以写得简洁一些，对于一些重要的定理，这个系数没有影响。\n在信号与系统中，我们知道如果希望信号经过一个系统后保持不变，那么这个系统的冲激响应应该是狄拉克函数 $\\delta(x)$ ，即 $\\delta(x)=0,x\\neq 0$ 且 $\\int_{-\\infty}^{\\infty} \\delta(x) \\, \\text{d}x=1$ 。这说明 $D_{n}(x)\\to\\delta(x),n\\to \\infty$ ，这一点可以通过求出 $D_{N}$ 的显示表达式得到： $$D_{N}(x)=\\frac{\\sin\\left( \\left( N+\\frac{1}{2} \\right)x \\right)}{\\sin(x/2)}.$$ 这不仅是 Dirichlet Kernel 的性质，也是其他 Kernel 的性质。\n定义了 Kernel 之后，部分和序列 $\\{ S_{n} \\}_{n=1}^N$ 就可以表示为原函数 $f(x)$ 与 Kernel 序列的卷积 $\\{ D_{n}*f(x) \\}_{n=1}^N$ 。这个卷积序列的收敛性和 $f(x)$ 傅立叶级数的收敛性是等价的，因为它本身就是从傅立叶级数变形得到的。将这个思路进行推广，给出函数列 $\\{ K_{n}(x) \\}$ ，然后将其与 $f(x)$ 卷积以得到一个函数列 $\\left\\{ K_{n}(x)*f(x) \\right\\}_{n=1}^\\infty$ ，部分和的收敛性简化为这个数列的收敛性。结论是，如果 $\\{ K_{N} \\}$ 满足\u0026quot;Good Kernel\u0026quot;的三个条件，那么当 $n\\to \\infty$ 时，卷积趋于 $f(x)$ ，当然，这要求 $f(x)$ 至少是连续的。\n这是一个关键的思路，如果我们证明了\u0026quot;Good Kernel\u0026quot;与 $f(x)$ 的卷积在 $n\\to \\infty$ 时收敛于 $f(x)$ ，那么我们可以只要求 $f(x)$ 连续，然后研究与其卷积的函数族是否是\u0026quot;Good Kernel\u0026quot;即可。\n这个意义上讲，函数列 $\\{ K_{n} \\}$ 是 $f(x)$ 与其傅立叶级数 $F(\\theta)$ 之间的近似器。然而不幸的是， $\\{ D_{N} \\}$ 并不是一个\u0026quot;Good Kernel\u0026quot;，这意味着傅立叶级数的收敛性问题的回答不一定是肯定的，傅立叶级数的无穷求和方式可能导致振荡十分剧烈，换言之，级数可能是发散的。\n新的问题也随之而来，既然傅立叶级数不一定收敛到原函数 $f(x)$ ，那么当 $f(x)$ 满足什么条件时，其傅立叶级数是收敛的，又是怎样收敛的（一致收敛，还是逐点收敛）？收敛性的后续讨论将在第三章进行。\n「我命令你收敛」：切萨罗求和与阿贝尔求和 #我们跳过收敛性的详细论证，考虑另一个问题。既然傅立叶级数的无穷求和可能导致级数发散，有没有一种方法令级数收敛呢？如果一个函数的傅立叶级数是振荡的，我们首先可以想到的是，由级数的部分和构成的序列平均是否是收敛的。例如序列 $1,-1,1,-1,\\dots$ ，它的部分和序列是 $1,0,1,0,\\dots$ 。虽然它是发散的，但部分和序列的均值收敛到了 $\\frac{1}{2}$ 。这样的求和方式与直接相加不同，称为切萨罗 （Cesàro）求和。如果级数的切萨罗和是收敛的，则称级数切萨罗可和。值得注意的是，如果级数在原先求和的意义下是收敛的，那么它一定是切萨罗可和的，切萨罗可和是收敛的一个推广。\n还可以进一步推广切萨罗求和，它就是阿贝尔（Abel）求和。阿贝尔求和将序列乘上一个指数衰减的因子 $r^k,0\\leq r\u003c1$ ，它的表达式为 $A(r)=\\sum_{k=0}^\\infty c_{k}r^k$ 。其中 $c_{0},\\dots,c_{n}$ 是序列。可以发现，阿贝尔求和是关于衰减因子 $r$ 的函数，如果要令序列 $\\{ c_{k} \\}_{k=0}^\\infty$ 是阿贝尔可和的，则需要 $A(r)$ 对于所有的 $0\\leq r\u003c1$ 都收敛，并且当 $r$ 趋近于 1 时， $A(r)$ 收敛到某个数 $s$ ： $\\lim_{ r \\to 1^- }A(r)=s$ 。\n级数收敛，切萨罗可和，阿贝尔可和的关系是：部分和收敛 $\\implies$ 切萨罗可和 $\\implies$ 阿贝尔可和，即部分和收敛时必定切萨罗可和，切萨罗可和时必定阿贝尔可和，但反之则不成立。可以用 Venn 图表示为：\n重复由卷积定义部分和得到 Dirichlet Kernel 的步骤，可以得到另外两种级数求和对应的 Kernel：\n切萨罗求和 $\\to$ 费叶核 阿贝尔求和 $\\to$ 泊松核 和 Dirichlet Kernel 不同的是，它俩都是好核，这意味着级数的收敛性得到了保证。最后，通过泊松核和卷积，解决第一章中提到单位圆盘的 Dirichlet 问题，也就是单位圆包含边界条件的热稳态方程的解。\n","date":"2024年3月7日","permalink":"/posts/steinfourier2-0/","section":"文章","summary":"简要的描述一下第二章的主要内容，涉及到傅立叶级数研究的对象，提出傅立叶级数的收敛性与唯一性问题，并由收敛性问题引申出级数求和的新方式。","title":"第二章 傅立叶级数的基本性质-概述"},{"content":"讨论话题\n","date":null,"permalink":"/topics/","section":"话题","summary":"讨论话题","title":"话题"},{"content":"","date":null,"permalink":"/","section":"内容","summary":"","title":"内容"},{"content":"最近发布的文章，按时间排序\n","date":null,"permalink":"/posts/","section":"文章","summary":"最近发布的文章，按时间排序","title":"文章"},{"content":"学习Stein《Fourier Analysis: Introduction》的笔记，我会尽可能地减少大段公式的出现，但有时这是不可避免的。\n","date":null,"permalink":"/topics/steinfourieranalysis/","section":"话题","summary":"\u003cp\u003e学习Stein《Fourier Analysis: Introduction》的笔记，我会尽可能地减少大段公式的出现，但有时这是不可避免的。\u003c/p\u003e","title":"Stein 傅立叶分析笔记"}]